{
    "player_name": "Caro",
    "rival_name": "Jake",
    "home_name": "viridian_city",
    "home_col": 28,
    "home_row": 17,
    "milestones": 31,
    "current_level_name": "pewter_city",
    "current_game_col": 24,
    "current_game_row": 43,
    "current_direction": 0,
    "seconds_played": 3345,
    "poke_dollars": 1265,
    "trainer_id": 25460,
    "defeated_npc_entries": [{ "level_name": "in_oaks_lab", "level_index": 11 }, { "level_name": "in_viridian_forest", "level_index": 13 }],
    "collected_npc_item_entries": [],
    "collected_npc_item_non_destructible_entries": [{ "level_name": "route_1", "level_index": 1 }],
    "bag": [{ "item_name": "TOWN_MAP", "item_quantity": 1 }, { "item_name": "POK^_BALL", "item_quantity": 5 }, { "item_name": "CANCEL", "item_quantity": 5 }],
    "pokedex": [0, 0, 0, 0, 0, 0, 0, 0, 0, 2, 0, 0, 0, 0, 0, 1, 0, 0, 0, 0, 0, 0, 0, 0, 2, 0, 0, 0, 0, 0, 0, 0, 0, 0, 0, 0, 0, 0, 0, 0, 0, 0, 0, 0, 0, 0, 0, 0, 0, 0, 0, 0, 0, 0, 0, 0, 0, 0, 0, 0, 0, 0, 0, 0, 0, 0, 0, 0, 0, 0, 0, 0, 0, 0, 0, 0, 0, 0, 0, 0, 0, 0, 0, 0, 0, 0, 0, 0, 0, 0, 0, 0, 0, 0, 0, 0, 0, 0, 0, 0, 0, 0, 0, 0, 0, 0, 0, 0, 0, 0, 0, 0, 0, 0, 0, 0, 0, 0, 0, 0, 0, 0, 0, 0, 0, 0, 0, 0, 0, 0, 0, 0, 1, 0, 0, 0, 0, 0, 0, 0, 0, 0, 0, 0, 0, 0, 0, 0, 0, 0, 0],
    "box_pokemon": [],
    "pokemon": [{ "species_name": "PIKACHU", "nickname": "PIKACHU", "level": 7, "current_hp": 3, "xp_points": 466, "status": 0, "rounds_to_awake": 0, "hp_iv": 7, "attack_iv": 6, "defense_iv": 9, "speed_iv": 11, "special_iv": 15, "hp_ev": 0, "attack_ev": 279, "defense_ev": 257, "speed_ev": 303, "special_ev": 235, "moveset": [{ "move_name": "THUNDERSHOCK", "pp_left": 18 }, { "move_name": "GROWL", "pp_left": 38 }, { "move_name": "TAIL_WHIP", "pp_left": 29 }] }, { "species_name": "CATERPIE", "nickname": "CATERPIE", "level": 5, "current_hp": 1, "xp_points": 125, "status": 0, "rounds_to_awake": 0, "hp_iv": 11, "attack_iv": 13, "defense_iv": 14, "speed_iv": 15, "special_iv": 13, "hp_ev": 0, "attack_ev": 0, "defense_ev": 0, "speed_ev": 0, "special_ev": 0, "moveset": [{ "move_name": "TACKLE", "pp_left": 35 }, { "move_name": "STRING_SHOT", "pp_left": 40 }] }]
}